jaustin/__init__.py
jaustin/color.py
jaustin/core.py
jaustin/jax.py
jaustin/timers.py
jaustin/torch.py
jaustin/cache/__init__.py
jaustin/cache/methodcache.py
jaustin/cache/picklecache.py
jaustin-0.0.8.dist-info/LICENSE
jaustin-0.0.8.dist-info/METADATA
jaustin-0.0.8.dist-info/WHEEL
jaustin-0.0.8.dist-info/top_level.txt
jaustin-0.0.8.dist-info/RECORD
