Metadata-Version: 2.1
Name: jaustin
Version: 0.0.8
Summary: A set of core Python utilities for machine learning and general programming
Home-page: https://github.com/jacobaustin123/jaustin
Author: Jacob Austin
Author-email: jacob.austin@columbia.edu
License: UNKNOWN
Platform: UNKNOWN
Classifier: Programming Language :: Python :: 3
Classifier: License :: OSI Approved :: MIT License
Classifier: Operating System :: OS Independent
Requires-Python: >=3.6
